[{"title":"英国因新冠病毒变异取消圣诞，英政客发推称「谢谢你，中国」，如何看待其言论？","url":"https://www.zhihu.com/question/435898356"},{"title":"「小丑竟是我自己」是个什么梗？反映了当代年轻人一种怎样的心理？","url":"https://www.zhihu.com/question/435578338"},{"title":"网传大连海洋大学一考研生确诊为新冠阳性，是否属实？目前情况如何了？","url":"https://www.zhihu.com/question/435956663"},{"title":"如何看待四川一小学生留字条后跳楼，称「我活得太累了，希望能多“睡”会」？我们应如何保护学生的心理健康？","url":"https://www.zhihu.com/question/435081629"},{"title":"如何看待女子穿婚纱在福州马拉松终点等待男友，但男友中途退赛？在哪里等比较合适以及冬天穿婚纱如何保暖？","url":"https://www.zhihu.com/question/435985864"},{"title":"有哪些高情商的聊天技巧？","url":"https://www.zhihu.com/question/327635458"},{"title":"如何看待普京将担任俄罗斯国务院主席？","url":"https://www.zhihu.com/question/435884120"},{"title":"如何看待热搜“郭德纲 不收女徒弟是因为尊重”被指歧视女性？","url":"https://www.zhihu.com/question/435928578"},{"title":"如何看待郑州一女子学校自习室偷走考研生平板，内含大量学习资料，被偷者称「心态有点崩」？","url":"https://www.zhihu.com/question/435959508"},{"title":"女生哪些行为一看就没谈过恋爱？","url":"https://www.zhihu.com/question/274051741"},{"title":"如何看待网传华为员工违规领夜宵被发现后，被罚终身不得领夜宵?","url":"https://www.zhihu.com/question/435580264"},{"title":"如何看待蒸汽平台(steam中国)即将于2021年1月16-17日的完美世界嘉年华推出试玩？","url":"https://www.zhihu.com/question/435824072"},{"title":"律师的真实收入有多恐怖？","url":"https://www.zhihu.com/question/360433896"},{"title":"如何看待张艺兴去湖师大附中招募练习生？","url":"https://www.zhihu.com/question/435453233"},{"title":"社区团购「九不得」新规出台：企业不得低价倾销、哄抬价格、利用大数据「杀熟」，将对行业带来哪些影响？","url":"https://www.zhihu.com/question/436014708"},{"title":"西安一幼师暴力提摔男童并用凳子砸，致其下巴缝 8 针，为何幼师伤童事件频繁发生？如何有效防止？","url":"https://www.zhihu.com/question/435946218"},{"title":"如何看待丁建强在隔离期间发的推文？","url":"https://www.zhihu.com/question/435936751"},{"title":"如何拒绝领导的工作要求？","url":"https://www.zhihu.com/question/269676467"},{"title":"每分钟翻倍的铜锣烧多久可以装满整个宇宙？","url":"https://www.zhihu.com/question/265508027"},{"title":"如何评价《英雄联盟》 2020 德杯小组赛 iG 翻盘击败 RNG？","url":"https://www.zhihu.com/question/436031064"},{"title":"斗胆请教，《红楼梦》想表达的终极内涵是什么？","url":"https://www.zhihu.com/question/54833966"},{"title":"甄嬛遇上魏璎珞，谁更厉害？","url":"https://www.zhihu.com/question/289923126"},{"title":"为何大米一般都是真空包装，而面粉不是？","url":"https://www.zhihu.com/question/333863779"},{"title":"反食品浪费法草案首次公开，制作「大胃王」、「暴食吃播」等音视频或被追责，这一法案具有怎样的意义？","url":"https://www.zhihu.com/question/435940839"},{"title":"为什么韦小宝舔到了阿珂，段誉却没舔到王语嫣?","url":"https://www.zhihu.com/question/430794863"},{"title":"神秘四奥中为什么大家觉得奥特之王最弱？","url":"https://www.zhihu.com/question/379593307"},{"title":"怎么看温铁军建议学习的日本农协？","url":"https://www.zhihu.com/question/397365295"},{"title":"LPL所谓盛产adc，真的叫的出名，国际扬名并且厉害的有哪些？","url":"https://www.zhihu.com/question/434401095"},{"title":"怎么把 Hello World 写的高端大气上档次？","url":"https://www.zhihu.com/question/434732218"},{"title":"给你一张中国地图，扔飞镖扔到哪里 2021 年就去哪里旅行你会参与吗？","url":"https://www.zhihu.com/question/435421386"},{"title":"15岁，无系统性训练，深蹲 150KG 卧推 100KG 在青少年中算什么水平？","url":"https://www.zhihu.com/question/435567872"},{"title":"如何看待自称暴雪电竞赛事运营总监的「夏花」被扒经历造假，众多电竞圈大佬遭欺骗？","url":"https://www.zhihu.com/question/435685913"},{"title":"研究生博士生到底喜欢逛哪些网站？","url":"https://www.zhihu.com/question/20809655"},{"title":"你觉得2020年最接近完美的笔记本电脑是哪一台？","url":"https://www.zhihu.com/question/435273110"},{"title":"这张 PPT 丑吗？","url":"https://www.zhihu.com/question/425510958"},{"title":"比特币在2020年底已经突破150000人民币一枚，你还认为它是一场骗局吗？","url":"https://www.zhihu.com/question/435820949"},{"title":"有哪些学生党必备的 App？","url":"https://www.zhihu.com/question/328315954"},{"title":"微信置顶语，有什么好的文案吗？","url":"https://www.zhihu.com/question/362629706"},{"title":"为什么洛伦兹力不会做功，而安培力可以？","url":"https://www.zhihu.com/question/21492495"},{"title":"宝宝添加辅食的先后顺序是怎样的？","url":"https://www.zhihu.com/question/434848356"},{"title":"考研要什么时候开始做准备？","url":"https://www.zhihu.com/question/333714747"},{"title":"iPad只能用Apple Pencil么？","url":"https://www.zhihu.com/question/359646795"},{"title":"英语零基础该如何准备考研 ？","url":"https://www.zhihu.com/question/56800185"},{"title":"在低谷中没有往上爬的勇气，怎么办？","url":"https://www.zhihu.com/question/434670651"},{"title":"你有迷茫的时候吗？","url":"https://www.zhihu.com/question/435541313"},{"title":"大家有没有可以和微信白色聊天框融为一体的背景图？","url":"https://www.zhihu.com/question/379486356"},{"title":"在职场上有没有推荐的书？","url":"https://www.zhihu.com/question/432190568"},{"title":"有什么生活中的道理，是到 30 岁才明白的？","url":"https://www.zhihu.com/question/426977689"},{"title":"为什么家猫被抛弃后很难在户外生存？","url":"https://www.zhihu.com/question/430534419"},{"title":"有没有听完脊背发凉的鬼故事？","url":"https://www.zhihu.com/question/424137859"}]