[{"title":"有没有发现本次奥运会国人不再唯金牌论了？","url":"https://www.zhihu.com/question/474810157"},{"title":"如何看待中国女子铁人三项运动员仲梦颖表示赛场的水质并没有异味，男子选手呕吐可能是因为太热？","url":"https://www.zhihu.com/question/475406361"},{"title":"如何看待安徽一教师在别墅补课被现场查处？怎样有效打击教师私下有偿补课？","url":"https://www.zhihu.com/question/475421091"},{"title":"东京奥运会乒乓球男单张本智和 3:4 不敌斯洛文尼亚选手无缘 8 强，如何评价他的表现？","url":"https://www.zhihu.com/question/475390740"},{"title":"河南卫辉城中水位居高不下，全城断水、断电、断路，众多群众被困，目前情况如何？","url":"https://www.zhihu.com/question/475343580"},{"title":"如何看待周杰伦、昆凌为郑州抗洪救灾捐款 300 万元？","url":"https://www.zhihu.com/question/475171933"},{"title":"如何看待俄罗斯女运动员戴游戏《巫师》猫学派项链夺得奥运会女子十米气手枪金牌，曾带狼学派项链夺亚军？","url":"https://www.zhihu.com/question/475024966"},{"title":"南京疫情确诊病例整体症状较轻，说明疫苗有保护作用，但接种新冠疫苗后为什么还会感染？","url":"https://www.zhihu.com/question/474183068"},{"title":"7 月 27 日四川新增本土确诊病例 3 例，28 日四川省发布疫情防控紧急通知，目前情况如何？","url":"https://www.zhihu.com/question/475484555"},{"title":"特朗普炮轰跨性别运动员参加女子项目：他们在夺走女性的权利，如何看待其观点？","url":"https://www.zhihu.com/question/475290957"},{"title":"如何看待贾秀全在女足惨败荷兰赛后表示「世界杯带队出线，奥运抢到亚洲名额，你觉得我成功还是失败」？","url":"https://www.zhihu.com/question/475423188"},{"title":"税前月薪 1.2W，租个 3K 的房子，奢侈吗？","url":"https://www.zhihu.com/question/470755124"},{"title":"7 月 27 日江苏新增本土病例 48 例，目前情况如何？","url":"https://www.zhihu.com/question/475496805"},{"title":"如何评价 A-Soul 的虚拟偶像「向晚（Ava）」的真人疑似暴露？","url":"https://www.zhihu.com/question/475463293"},{"title":"K12 校外教育培训遇冷的情况下，那些在此行业的教师该何去何从呢？","url":"https://www.zhihu.com/question/474516351"},{"title":"如何看待东京奥运会体操女子团体决赛拜尔斯跳马成绩不佳，并且在跳马后就退赛？这会带来什么影响？","url":"https://www.zhihu.com/question/475390625"},{"title":"如果我上场十分钟必进一球，每场一次。其他时间就是体测勉强过线的大学生水平，那我的身价大概会在多少?","url":"https://www.zhihu.com/question/472960919"},{"title":"《红楼梦》想表达的终极内涵是什么？","url":"https://www.zhihu.com/question/54833966"},{"title":"《海贼王》世界里，一个人吃两个恶魔果实就会死，为什么海军不喂四皇恶魔果实来变相毒杀他们？","url":"https://www.zhihu.com/question/469908655"},{"title":"做程序员是真的因为喜欢吗？还是因为收入比较高？","url":"https://www.zhihu.com/question/473184827"},{"title":"如何看待鸿星尔克董事长请求网友理性消费？","url":"https://www.zhihu.com/question/474886857"},{"title":"南京疫情传播链已关联多个省市，暴露了禄口机场及各地防疫的哪些问题？该如何弥补？","url":"https://www.zhihu.com/question/475413870"},{"title":"甘肃一载 63 人大巴车冲出高速，已致 13 人 遇难，3 人被公安机关控制，目前具体情况如何？","url":"https://www.zhihu.com/question/475107363"},{"title":"如何评价中兴官宣将于 7 月 27 日发布屏下摄像头手机 Axon30 ？","url":"https://www.zhihu.com/question/473225793"},{"title":"孩子非常喜欢乒乓球，看到奥运会乒乓球混双决赛输了非常伤心，该如何安慰孩子？","url":"https://www.zhihu.com/question/475164928"},{"title":"大城市里打拼的年轻人真的像《我在他乡挺好的》里演得一样难吗？","url":"https://www.zhihu.com/question/473665579"},{"title":"如何激怒一位《哈利波特》原著党？","url":"https://www.zhihu.com/question/427219865"},{"title":"为什么《明日方舟》这次夏活更新会引发这么大的争议?","url":"https://www.zhihu.com/question/475331625"},{"title":"两个人 1000 元去重庆旅游 2 天够吗？","url":"https://www.zhihu.com/question/472417007"},{"title":"东京奥运会开幕至今，哪些运动员和比赛让你记忆深刻，你心中的「最强」运动员是谁？","url":"https://www.zhihu.com/question/475299083"},{"title":"《红楼梦》中你最希望哪个丫鬟伺候你？","url":"https://www.zhihu.com/question/375863795"},{"title":"如何看待华为免去苏箐智能驾驶产品部部长职务？还有哪些信息值得关注？","url":"https://www.zhihu.com/question/475376533"},{"title":"怎么才能让皮肤越来越白?","url":"https://www.zhihu.com/question/458127901"},{"title":"如何看待即将于 10 月 15 日正式面世的游戏《仙剑奇侠传七》？","url":"https://www.zhihu.com/question/475512253"},{"title":"适合大学寝室的速食早餐有哪些？","url":"https://www.zhihu.com/question/27079269"},{"title":"有哪些曾经是奢侈食品现在却变得平民化的食物？","url":"https://www.zhihu.com/question/466302067"},{"title":"在社会上，单纯善良一定吃亏，偷奸耍滑一定占便宜吗?","url":"https://www.zhihu.com/question/473914745"},{"title":"如何看待陈铭《立场》采访中家长「没游戏就没这个问题了」的观点，没了游戏世界会更好吗？","url":"https://www.zhihu.com/question/475175315"},{"title":"如何评价《北辙南辕》编剧回应剧情悬浮「这就是我的地气，我的生活」？反映了什么问题？","url":"https://www.zhihu.com/question/475474703"},{"title":"有没有日常朋友圈发的简短文案？","url":"https://www.zhihu.com/question/474133422"},{"title":"如何评价电视剧《大决战》？","url":"https://www.zhihu.com/question/467711149"},{"title":"暑促来临，有哪些游戏本值得关注？","url":"https://www.zhihu.com/question/474389977"},{"title":"有没有什么好用的美白精华？","url":"https://www.zhihu.com/question/313635834"},{"title":"23岁，开始害怕 30 岁还碌碌无为，却不知道如何前进，该怎么办？","url":"https://www.zhihu.com/question/471080839"},{"title":"即将去读研究生，有什么建议吗？","url":"https://www.zhihu.com/question/455377407"},{"title":"如何看待美国男篮奥运会首战失利？为什么感觉他们在NBA特别厉害，结果到了奥运会就开始失利？","url":"https://www.zhihu.com/question/474990207"},{"title":"为什么我会觉得二次元里的双马尾好看，三次元里的双马尾就不是很戳?","url":"https://www.zhihu.com/question/449620519"},{"title":"如何看待某博主在《未定事件簿》推广视频中疑似嘲讽游戏角色、惹恼游戏玩家？","url":"https://www.zhihu.com/question/475183502"},{"title":"2020 东京奥运赛艇女子四人双桨决赛中国队夺得第 10 金，如何评价她们的表现？","url":"https://www.zhihu.com/question/475488344"},{"title":"射击运动员和特种兵谁的枪法更准？","url":"https://www.zhihu.com/question/469107554"}]