[{"title":"警方通报成都 49 中学生坠亡：排除刑案，家属对调查结论无异议，还有哪些信息值得关注？","url":"https://www.zhihu.com/question/458909971"},{"title":"如何看待我国 2020 年出生人口为 1200 万人，处于较低生育水平？这一数字意味着什么？","url":"https://www.zhihu.com/question/458828004"},{"title":"如何看待路透社报道：腾讯正在与美国谈判保留在 Riot 和 Epic 的股份？","url":"https://www.zhihu.com/question/458041957"},{"title":"武汉大风中吊篮撞楼两人死亡，家属称「事发前工人曾电话求救，赶到后遭围殴抢手机」，还有哪些细节值得关注？","url":"https://www.zhihu.com/question/458864077"},{"title":"大学生发现免费吃肯德基套餐「方法」分享给同学并从中牟利，获刑 2 年半，你怎么看？","url":"https://www.zhihu.com/question/458862544"},{"title":"如何看待漫画《进击的巨人》最终话「加页」部分的情报？","url":"https://www.zhihu.com/question/458937970"},{"title":"如何看待某剧组在南京大学拍戏遇冷，学生不围观、不追星？这一现象反映了什么？","url":"https://www.zhihu.com/question/458770659"},{"title":"有哪些看起来有点大病的“冷知识”？","url":"https://www.zhihu.com/question/458360832"},{"title":"官方通报成都 49 中学生坠亡「基本判断因个人问题轻生」，新华社评校方「避重就轻」，哪些信息值得关注？","url":"https://www.zhihu.com/question/458795206"},{"title":"如何看待外媒发文《中国粉丝正如何在世界上强化中国「民族主义」》？","url":"https://www.zhihu.com/question/458741420"},{"title":"技嘉科技就嘲讽中国制造道歉：官网发布部分文字与事实严重不符，将加强内部管理，你怎么看？","url":"https://www.zhihu.com/question/458846399"},{"title":"5.12 汶川地震过去 13 年了，四川汶川人民是怎样度过这些年的？你对汶川地震最深刻的印象是什么？","url":"https://www.zhihu.com/question/458967831"},{"title":"飞机上不打开飞行模式会被发现吗？","url":"https://www.zhihu.com/question/448267257"},{"title":"不吹不黑，你觉得《王者荣耀》里开团能力最强的英雄是谁？","url":"https://www.zhihu.com/question/457720589"},{"title":"林郑月娥称香港将与内地公务员互换「挂职」，对此你怎么看？","url":"https://www.zhihu.com/question/458804652"},{"title":"外国人眼中的汉字是怎样的？","url":"https://www.zhihu.com/question/35963650"},{"title":"为什么现在的年轻人明明都没有老一辈那么辛苦，反而身上的疾病好像还变多了呢？","url":"https://www.zhihu.com/question/458382123"},{"title":"如何看待重庆老爸长期用「激将法教育」，刺激三岁儿子：如果不乖，就把东西给妹妹，致使儿子讨厌并欺负妹妹？","url":"https://www.zhihu.com/question/458830152"},{"title":"国家统计局：中国家庭户规模继续缩小，平均每个家庭户人口为 2.62 人，意味着什么？会带来哪些影响？","url":"https://www.zhihu.com/question/458817764"},{"title":"如何看待兰州一小区禁止特斯拉入内，相关单位是否有权禁止特斯拉通行？主要的考虑是什么？","url":"https://www.zhihu.com/question/458089175"},{"title":"牙齿正畸的朋友们后悔了吗？","url":"https://www.zhihu.com/question/308980503"},{"title":"你知道哪些餐饮界的暴利菜品？","url":"https://www.zhihu.com/question/430100068"},{"title":"女生 27 岁考研是否值得？","url":"https://www.zhihu.com/question/443951009"},{"title":"《王者荣耀》里最难死的中单英雄是谁？","url":"https://www.zhihu.com/question/458262505"},{"title":"如何评价漫画家谏山创最近的访谈内容？","url":"https://www.zhihu.com/question/457336083"},{"title":"养了一年的小猫咪，我想放回大自然怎么办？","url":"https://www.zhihu.com/question/457533958"},{"title":"为什么手机计算器上50%+50%=0.75?","url":"https://www.zhihu.com/question/453500291"},{"title":"如何评价2021 年 5 月 11日 英特尔发布的 11 代高性能移动端处理器？有哪些亮点和不足？","url":"https://www.zhihu.com/question/458908921"},{"title":"如何评价《海贼王》第 1013 话情报？","url":"https://www.zhihu.com/question/458923937"},{"title":"周杰伦究竟有多厉害？","url":"https://www.zhihu.com/question/284816654"},{"title":"你觉得动画《火影忍者》中塑造最成功的角色是谁？","url":"https://www.zhihu.com/question/456497122"},{"title":"能预测一下 2021 年的高考语文作文吗？","url":"https://www.zhihu.com/question/451864903"},{"title":"你家的猫都有哪些怪癖？","url":"https://www.zhihu.com/question/458176825"},{"title":"如果一个女生喜欢你会有什么表现？","url":"https://www.zhihu.com/question/456917552"},{"title":"有哪些相对容易拿奖的大学生竞赛？","url":"https://www.zhihu.com/question/274650982"},{"title":"孩子不穿袜子光脚在地上玩，会感冒吗？","url":"https://www.zhihu.com/question/458311930"},{"title":"高考政治大题怎么做?","url":"https://www.zhihu.com/question/61907146"},{"title":"第七次人口普查结果公布，如何看待我国60岁及以上人口超2.64亿？","url":"https://www.zhihu.com/question/458815573"},{"title":"五月准备考研来得及吗？","url":"https://www.zhihu.com/question/455366966"},{"title":"有哪些值得推荐的关于死亡教育的绘本？","url":"https://www.zhihu.com/question/438988922"},{"title":"有娃的那天就想着孩子健康快乐就好，可孩子上学后似乎没有不想孩子优秀的父母，但优秀只有「鸡娃」一条路吗？","url":"https://www.zhihu.com/question/454214876"},{"title":"如果肝不好，最好少吃哪些食物？","url":"https://www.zhihu.com/question/435738194"},{"title":"INTO1 宿舍分配已出，大家对宿舍和宿舍分配满意吗？","url":"https://www.zhihu.com/question/458665728"},{"title":"对于久坐的人，屁股下加个坐垫有用吗？","url":"https://www.zhihu.com/question/355087220"},{"title":"第七次人口普查数据，广东和山东人口超过1亿人，各省份人口数据有何亮点？","url":"https://www.zhihu.com/question/458855355"},{"title":"如果《让子弹飞》当中被污蔑吃凉粉的是你，你该怎么办？","url":"https://www.zhihu.com/question/333769627"},{"title":"《王者荣耀》里，同位置克制关系最大的是哪一对英雄？","url":"https://www.zhihu.com/question/456526948"},{"title":"高考生物大题怎么表述才能得分？","url":"https://www.zhihu.com/question/385995155"},{"title":"离职交接的最后一个月还被领导疯狂压榨怎么办？","url":"https://www.zhihu.com/question/455719427"},{"title":"减肥二十斤的人容貌变化有多大？","url":"https://www.zhihu.com/question/339245837"}]