[{"title":"假如你为家乡代言，你最想介绍家乡的哪些新变化？","url":"https://www.zhihu.com/question/428870087"},{"title":"大连一自称教师女子发表言论称「希望大连疫情越多越好」，目前已被依法行拘，如何评价这一事件？","url":"https://www.zhihu.com/question/499587337"},{"title":"巨石强森称想和吴京合作，透露两人之前有过会面，你期待他们俩的合作吗？","url":"https://www.zhihu.com/question/498999704"},{"title":"如何看待腾讯端游《天涯明月刀》疑似游戏托被发现，引发游戏玩家删号？","url":"https://www.zhihu.com/question/499532796"},{"title":"男子因太能吃被「自助」餐厅拉黑，餐厅此种行为合法吗？","url":"https://www.zhihu.com/question/499739058"},{"title":"如何看待华为发布口红耳机 FreeBuds Lipstick？","url":"https://www.zhihu.com/question/499650029"},{"title":"武磊赛后采访称「外界不了解我们的艰苦」，国足本届世预赛经历了哪些困难？是否真的压力过大?","url":"https://www.zhihu.com/question/499466090"},{"title":"国美就「通报员工摸鱼事件」后发声，称「将追究内部文件外泄责任」，如何看待此发声？反映了哪些问题？","url":"https://www.zhihu.com/question/499740646"},{"title":"如何看待「进口猕猴桃比国产价格贵十倍」？区别在哪里？","url":"https://www.zhihu.com/question/499585675"},{"title":"古代生产力较低，物资比较缺乏，为什么古人却选择宽袍大袖这种明显浪费布料的服装样式呢？","url":"https://www.zhihu.com/question/497927992"},{"title":"拜登签下基建法案后称「明年美国基础设施投资增速将 20 年来首次超过中国」，该法案实际成效将如何？","url":"https://www.zhihu.com/question/499568874"},{"title":"为什么说「住五星级酒店比上班还要累」？你有过哪些类似经历？","url":"https://www.zhihu.com/question/499551110"},{"title":"你见过哪些有意思的 WiFi 名字或 WiFi 密码？","url":"https://www.zhihu.com/question/499253466"},{"title":"苹果宣布推出自助维修计划，用户可自行购买零件更换，这对于用户来说意味着什么？","url":"https://www.zhihu.com/question/499678057"},{"title":"时隔近一年为什么腾讯还没有拿出来像样的《原神》竞品？","url":"https://www.zhihu.com/question/473981288"},{"title":"如何看待「00 后女大学生毕业做私人保镖」？大学生有哪些让你意想不到的就业方式？","url":"https://www.zhihu.com/question/499181405"},{"title":"如何看待曾因踩踏陕西榆林丹霞地貌被批的「冒险雷探长」获榆林市授予「文化和旅游推广大使」？","url":"https://www.zhihu.com/question/499557705"},{"title":"明年毕业的在校应届生，找了几个觉得还行的工作，但在网上一搜 90% 以上都是对公司差评，我该怎么办？","url":"https://www.zhihu.com/question/498950804"},{"title":"11 月 18 日国家反垄断局正式挂牌成立，其成立具有哪些意义？将会发挥怎样的作用？","url":"https://www.zhihu.com/question/499733373"},{"title":"嘀嗒出行回应女乘客跳车「暂停司机接单，呼吁用户平和沟通」，如何看待这起纠纷？如何杜绝司机违规拼单现象？","url":"https://www.zhihu.com/question/499741964"},{"title":"如何看待中山大学在 97 周年校庆，不征集校友意见更换校徽，由绿色改为红色？","url":"https://www.zhihu.com/question/499178449"},{"title":"如何评价杨幂主演的电视剧《斛珠夫人》评分 4.9？","url":"https://www.zhihu.com/question/499434257"},{"title":"FPX 官宣上单选手 Nuguri 断开连接，如何评价他在 FPX 效力期间的表现？你觉得他会去哪？","url":"https://www.zhihu.com/question/499568659"},{"title":"如何看待网传联发科新一代芯片命名为「天玑 9000」？这出于怎样的考虑？","url":"https://www.zhihu.com/question/499287270"},{"title":"江苏启东就「三名学生坠楼事件」回应，称「排除他人所为，与游戏无关」，目前情况如何？","url":"https://www.zhihu.com/question/499592151"},{"title":"如何评价张艺兴在第28届东方风云榜音乐盛典的《苦行僧》和《飞天》舞台？","url":"https://www.zhihu.com/question/499667931"},{"title":"老公沉迷《魔兽世界》，白天只要在家就在玩游戏，该怎么沟通解决？","url":"https://www.zhihu.com/question/492997580"},{"title":"辅助生殖技术需求飙升，我国每年约 30 万名试管婴儿诞生，如何看待这一趋势？为何不孕不育人群增多了？","url":"https://www.zhihu.com/question/486945391"},{"title":"为什么我感觉游戏王的剧情很烂，为啥打牌可以影响社会地位？","url":"https://www.zhihu.com/question/441703528"},{"title":"乾隆白菜到底是凉菜还是啥东西？怎么做更正宗？","url":"https://www.zhihu.com/question/498597978"},{"title":"想给女朋友换个手机，是给她买个二手 iPhone12 还是买个全新的小米 Civi？","url":"https://www.zhihu.com/question/498814168"},{"title":"如何评价《原神》获得 2021 年 TGA 最佳持续运营、最佳移动（手机）游戏两项提名？","url":"https://www.zhihu.com/question/499584716"},{"title":"月薪 6000 元，老婆要我求婚买 1 万多的钻戒，过分吗?","url":"https://www.zhihu.com/question/497817018"},{"title":"顾佳给许幻山买橘子这件事，高明吗？高明在哪里？","url":"https://www.zhihu.com/question/485114644"},{"title":"如何评价 EDG 中单选手 Scout（李汭燦）？","url":"https://www.zhihu.com/question/55043077"},{"title":"金庸的十四部作品中为什么有一半的作品知名度不高？","url":"https://www.zhihu.com/question/498848249"},{"title":"动画《时光代理人》中的角色在现实中有原型吗？如何成功塑造角色？","url":"https://www.zhihu.com/question/499172076"},{"title":"如何看待今年互联网行业的应届生薪资是制造业薪资的四倍（甚至十倍），请问将来从事制造业的我们该怎么办？","url":"https://www.zhihu.com/question/492426982"},{"title":"线上购买旅游门票有什么好处吗？","url":"https://www.zhihu.com/question/499557378"},{"title":"《原神》2.3 版本后角色池为什么要出「双up」？","url":"https://www.zhihu.com/question/498573246"},{"title":"中国足球下一批归化球员都有可能有谁？","url":"https://www.zhihu.com/question/498952507"},{"title":"请问大家的科二都考了几次才通过？","url":"https://www.zhihu.com/question/498499597"},{"title":"正确的刷牙方式是什么？电动牙刷值得买吗？","url":"https://www.zhihu.com/question/486968186"},{"title":"有哪些让你吹爆的高颜值好物？","url":"https://www.zhihu.com/question/426328147"},{"title":"当科研助理，做得好可以发文章吗？有机会转去读博吗？","url":"https://www.zhihu.com/question/497159317"},{"title":"能干成大事的人都是什么样的人？","url":"https://www.zhihu.com/question/426658242"},{"title":"你对年轻人的第一份工作有什么建议吗？","url":"https://www.zhihu.com/question/497729291"},{"title":"有什么小物件能够显著地提高幸福感（幸福指数）？","url":"https://www.zhihu.com/question/23535906"},{"title":"2021 年两院院士增选结果揭晓，149 人当选，有哪些亮点值得关注？","url":"https://www.zhihu.com/question/499703546"},{"title":"为什么越来越多的年轻人选车更喜欢选中国哈弗？","url":"https://www.zhihu.com/question/499686550"}]