[{"title":"如何看待教育部通报湖北某考生考中作弊，将手机夹在衣服中带入考场，系考中个人作弊，不存在考前泄题?","url":"https://www.zhihu.com/question/463998872"},{"title":"乌合麒麟联合植物学家曾孝濂创作的作品《岛》，画面有哪些值得关注的细节？","url":"https://www.zhihu.com/question/463946010"},{"title":"网友称游泳馆每天都有女性带十多岁大男孩进女更衣室，如何看待这种行为？","url":"https://www.zhihu.com/question/463887838"},{"title":"如何看待重庆本科生路边通宵洗车，称面子不重要，重要是为梦想奋斗？你是否认同？","url":"https://www.zhihu.com/question/463828183"},{"title":"疫情期间台湾现大量离境人潮，台学者称「赴大陆打疫苗人数或不亚于赴美」，会产生哪些影响？","url":"https://www.zhihu.com/question/463915254"},{"title":"2022QS 世界大学排名发布，清华北大跻身前 20，国内大学排名创纪录，还有哪些信息值得关注？","url":"https://www.zhihu.com/question/463988313"},{"title":"网友质疑北大老师韦东奕教学水平呆板，有观点称「北大学生无需生动的讲解」，实际情况如何？","url":"https://www.zhihu.com/question/463589084"},{"title":"如何看待青山周平在《梦想改造家》的改造被「糟蹋」？是设计的问题，还是屋主浪费了一番苦心？该感到可惜吗？","url":"https://www.zhihu.com/question/462730740"},{"title":"如何看待三家银行宣布支持鸿蒙操作系统，具有怎样的实际意义？","url":"https://www.zhihu.com/question/463778303"},{"title":"如何看待中山大学 2021 年招生大类及分流专业？","url":"https://www.zhihu.com/question/463925066"},{"title":"美国称追回付给黑客的大部分比特币赎金，对于比特币交易来说意味着什么？","url":"https://www.zhihu.com/question/463845692"},{"title":"福建考试院证实福州一考点语文考试提前两分多钟打铃，有哪些影响？后续会怎么处理？","url":"https://www.zhihu.com/question/463943012"},{"title":"机密文件首次证实：东条英机等 7 名甲级战犯骨灰被美军扬进太平洋，这意味着什么？","url":"https://www.zhihu.com/question/463707211"},{"title":"如何看待罗翔回忆年轻时没能为衣衫褴褛的老太太提供法律援助的经历？","url":"https://www.zhihu.com/question/464013828"},{"title":"如何评价 2021 年高考全国乙卷理综？","url":"https://www.zhihu.com/question/463841934"},{"title":"如何看待中国美院学生的行为艺术作品《植入》：手握一抔土 10 天后长草？","url":"https://www.zhihu.com/question/463307719"},{"title":"河北考生因戴金属牙套不让进考场，官方通报称「实际和报道不吻合」，哪些问题值得关注？类似规定是否合理？","url":"https://www.zhihu.com/question/463806366"},{"title":"终于明白为什么有的人宁愿趴在图书馆午休一会也不回宿舍，对此大家怎么看？","url":"https://www.zhihu.com/question/456455985"},{"title":"《王者荣耀》触发 ELO 机制怎么办?","url":"https://www.zhihu.com/question/341453743"},{"title":"如何评价 2021 年各卷高考文综题？哪科最难？有哪些变化？","url":"https://www.zhihu.com/question/463595992"},{"title":"上海复旦大学一教师捅死同事，犯罪嫌疑人已被控制，可能需要承担怎样的法律责任？哪些问题值得关注？","url":"https://www.zhihu.com/question/463773359"},{"title":"如何看待手机游戏《摩尔庄园》背后的「吉比特」公司股价一周内暴涨 25%，市值涨超 100 亿？","url":"https://www.zhihu.com/question/463704962"},{"title":"如何评价索尼于 6 月 9 日正式发布的 WF-1000XM4 真无线蓝牙降噪耳机？","url":"https://www.zhihu.com/question/463984969"},{"title":"勒布朗詹姆斯不去报团会得总冠军吗？","url":"https://www.zhihu.com/question/454555704"},{"title":"2021 年 6 月显卡价格趋势怎么样了？","url":"https://www.zhihu.com/question/462608710"},{"title":"高考场外父亲举牌「不管考的怎么样，爸爸妈妈都很爱你」，你高考时父母是如何鼓励你的？","url":"https://www.zhihu.com/question/463920865"},{"title":"假如世界多出来一个誓死效忠你的人，你会怎么做？","url":"https://www.zhihu.com/question/462848357"},{"title":"安卓1.0明显是基于linux内核开发的，安卓1.0是不是linux套壳？","url":"https://www.zhihu.com/question/463995705"},{"title":"高考结束后心里空落落的，该干点啥好呢？好难过啊，如何排解这种情绪？","url":"https://www.zhihu.com/question/463903480"},{"title":"如何评价游戏《原神》稻妻的新角色「红叶逐荒波 · 枫原万叶」？","url":"https://www.zhihu.com/question/463721255"},{"title":"孩子在幼儿园被打，应不应该打回去？还有哪些更好的处理办法？","url":"https://www.zhihu.com/question/462300016"},{"title":"新手怎么备考事业单位？","url":"https://www.zhihu.com/question/434514549"},{"title":"应该如何教孩子妥善地控制自己的情绪？","url":"https://www.zhihu.com/question/382636157"},{"title":"如何评价朱一龙在电视剧《叛逆者》中的表现？","url":"https://www.zhihu.com/question/388819632"},{"title":"为什么婴儿更喜欢被抱着睡？","url":"https://www.zhihu.com/question/454465321"},{"title":"有哪些甜甜的小故事？","url":"https://www.zhihu.com/question/267054901"},{"title":"35岁以后的全职妈妈还能干什么？","url":"https://www.zhihu.com/question/434588539"},{"title":"高考之后毕业旅行想去海边有哪些推荐？","url":"https://www.zhihu.com/question/459020761"},{"title":"高考正当时，南京大学招生宣传引争议，这一宣传方式是否妥当？","url":"https://www.zhihu.com/question/463702038"},{"title":"新人作家，听说网文不能写楔子引言，但是我看《完美世界》就有楔子，我这样写需要切吗?","url":"https://www.zhihu.com/question/463814502"},{"title":"「睾丸是和大脑最像的人体器官」这一结论有什么实际意义么？","url":"https://www.zhihu.com/question/463156456"},{"title":"中国超 2 亿人单身，一个人住如何提升生活品质？","url":"https://www.zhihu.com/question/455461691"},{"title":"如何评价《原神》七月即将上线的稻妻？","url":"https://www.zhihu.com/question/463180681"},{"title":"买房时要避开哪些楼层？","url":"https://www.zhihu.com/question/447920355"},{"title":"《叛逆者》第一二集里，为什么军统情报站长陈默群要带新人林楠笙参与绝密任务？","url":"https://www.zhihu.com/question/463747393"},{"title":"如何评价电视剧《叛逆者》中朱一龙饰演的林楠笙？","url":"https://www.zhihu.com/question/463814765"},{"title":"2021 年 618 有哪些手机值得入手？","url":"https://www.zhihu.com/question/457255298"},{"title":"2021年618有哪些值得入手的家居好物？","url":"https://www.zhihu.com/question/460447642"},{"title":"六级听力如何上二百？","url":"https://www.zhihu.com/question/361688103"},{"title":"王小波到底是什么样的存在？","url":"https://www.zhihu.com/question/27333174"}]