[{"title":"如何看待专家称日本核废水可致「三致」，致癌致畸致突变，对人的遗传基因有重大的影响，该如何防范？","url":"https://www.zhihu.com/question/454262625"},{"title":"你对于何炅父亲被强制执行这件事怎么看？如果何炅爸爸名下没有资产可以让何炅还吗？","url":"https://www.zhihu.com/question/454384646"},{"title":"RNG 3:2 EDG 挺进总决赛，如何评价这场比赛？","url":"https://www.zhihu.com/question/454422605"},{"title":"为什么古代大炮攻城不直接对城门开炮？","url":"https://www.zhihu.com/question/363815303"},{"title":"有哪些曾经常见的食材淡出了中国人的食谱？","url":"https://www.zhihu.com/question/49690737"},{"title":"苹果公司宣布 4 月 20 日举行新品发布会，有哪些值得关注的信息？","url":"https://www.zhihu.com/question/454502427"},{"title":"《王者荣耀》巅峰前十玩家出现华东理工学生，昵称「欢迎考华理」，这波操作会吸引高考生报考吗?","url":"https://www.zhihu.com/question/454324463"},{"title":"我让六年级儿子揭发班级大队长抄他答案，这个方法欠妥吗？","url":"https://www.zhihu.com/question/453509757"},{"title":"四川高院回应成都岳父杀害女婿一家三口案正在依法评查，该案二审改判死缓是否合理？有哪些信息值得关注？","url":"https://www.zhihu.com/question/454370183"},{"title":"如何看待郑州一渣土车疑似闯红灯，为躲避电动车侧翻，导致越野车司机丧命?渣土车司机需要承担哪些法律责任？","url":"https://www.zhihu.com/question/454243355"},{"title":"如果林平之把辟邪剑谱公开了，那当时的江湖中人会练吗?","url":"https://www.zhihu.com/question/442262894"},{"title":"山东菏泽发现 156 座连片汉墓，考古价值有多高？对菏泽的发展有什么影响?","url":"https://www.zhihu.com/question/454325320"},{"title":"请问 985、211 有多美好？","url":"https://www.zhihu.com/question/438353781"},{"title":"如何看待Siri曝光4月20号的apple event，是否会在当天发布新品？","url":"https://www.zhihu.com/question/454424112"},{"title":"如何看待美国务院发言人用「赞赏」一词评价日本核污水排海事件？","url":"https://www.zhihu.com/question/454360398"},{"title":"贫贱夫妻百事哀能哀到什么地步？","url":"https://www.zhihu.com/question/363473759"},{"title":"为什么空调房里没蚊子？","url":"https://www.zhihu.com/question/26007726"},{"title":"福特Mustang Mach-E售价26.5-37.99万元，相比特斯拉Model Y有竞争力吗？","url":"https://www.zhihu.com/question/454461610"},{"title":"日本政府在宣布正式排核污水入海后，竟然制作了「放射性氚」吉祥物，你怎么看？","url":"https://www.zhihu.com/question/454524195"},{"title":"女足奥预赛附加赛王霜梅开二度，中国女足 2:2 总比分 4:3 淘汰韩国进军奥运，如何评价本场比赛？","url":"https://www.zhihu.com/question/454448624"},{"title":"你见过的最能吃的人有多能吃？","url":"https://www.zhihu.com/question/40594129"},{"title":"在飞机头等舱，坐过你旁边的最著名的人是谁？","url":"https://www.zhihu.com/question/359274010"},{"title":"《甄嬛传》甄嬛复宠大费周章，为何沈眉庄扔个镯子就能重获圣心？","url":"https://www.zhihu.com/question/454262368"},{"title":"如何看待江西一红黄蓝幼儿园男幼师发男童闻脚图，并配文「从小培养 m 」，官方回应：已停职接受调查？","url":"https://www.zhihu.com/question/454361643"},{"title":"研究生学历真的重要吗?","url":"https://www.zhihu.com/question/346149746"},{"title":"《进击的巨人》作者谏山创的精神状态是不是不稳定?","url":"https://www.zhihu.com/question/453646269"},{"title":"《海贼王》里，为何赤犬作为很早就出场的强者，他的压迫感没有掉价？","url":"https://www.zhihu.com/question/453269002"},{"title":"剧本杀凭什么能卖那么贵？","url":"https://www.zhihu.com/question/448110702"},{"title":"如何看待「迟到学生讲台站一排被老师掌掴」，校方回应称涉事教师已停职，并开全校大会当面给学生道歉？","url":"https://www.zhihu.com/question/454399314"},{"title":"异地恋都是怎么分手的？","url":"https://www.zhihu.com/question/277457122"},{"title":"机械硬盘有多脆弱？","url":"https://www.zhihu.com/question/23637714"},{"title":"如何评价微软正式发布的 Surface Laptop 4?","url":"https://www.zhihu.com/question/454473220"},{"title":"脸大并且好看是一种什么样的体验？","url":"https://www.zhihu.com/question/31516781"},{"title":"让尤弥尔爱上初代王的设定，是不是整个《进击的巨人》最大的败笔？","url":"https://www.zhihu.com/question/453484164"},{"title":"被相亲对象吊着是什么感觉？","url":"https://www.zhihu.com/question/453284347"},{"title":"金庸小说里，最悲伤的话是什么？","url":"https://www.zhihu.com/question/37039573"},{"title":"有哪些一个镜头就体现一个演员是否会演戏的例子？","url":"https://www.zhihu.com/question/269939406"},{"title":"Netflix宣布将制作、上线真人版《机动战士高达》电影，由《金刚骷髅岛》导演执导，你看好这次改编吗？","url":"https://www.zhihu.com/question/454373008"},{"title":"有很甜的恋爱故事吗？","url":"https://www.zhihu.com/question/336465537"},{"title":"汉人在清朝算是怎样的处境？","url":"https://www.zhihu.com/question/454255663"},{"title":"如何看待「如果屠宰场的外墙是玻璃做的，你也会是一个素食者」的言论？","url":"https://www.zhihu.com/question/38817519"},{"title":"如何备考2022年法硕（非法学）？","url":"https://www.zhihu.com/question/398179108"},{"title":"用日语代替英语高考好吗？","url":"https://www.zhihu.com/question/21682886"},{"title":"有什么看起来特别虐，看了心疼的句子？","url":"https://www.zhihu.com/question/453352588"},{"title":"即将播出的《皓衣行》你觉得陈飞宇和罗云熙会爆吗？","url":"https://www.zhihu.com/question/451189105"},{"title":"有哪些值得英语专业反复观看的英文电影？","url":"https://www.zhihu.com/question/327827779"},{"title":"传统豪华品牌车企能否在电动化领域继续保持领先优势？","url":"https://www.zhihu.com/question/358930164"},{"title":"如果你是替身文里被替身的女二，你会怎么做？","url":"https://www.zhihu.com/question/394589030"},{"title":"如何以「我被我们家车子监视了」为开头写一个故事？","url":"https://www.zhihu.com/question/445381774"},{"title":"健康管理师含金量到底有多少？","url":"https://www.zhihu.com/question/339113381"}]