[{"title":"如何看待宝宝霜「益芙灵」「开心森林」激素含量超标，婴儿用后成「大头娃娃」？这种产品为什么会流入市场？","url":"https://www.zhihu.com/question/438275588"},{"title":"如何看待 1 月 7 日拼多多又一员工被救护车拉走，经诊断为肠痉挛？","url":"https://www.zhihu.com/question/438304813"},{"title":"如何看待全国多地发出「非必要不返乡」倡议，提倡「就地过年」？今年你会回家过年吗？","url":"https://www.zhihu.com/question/437957211"},{"title":"长沙 22 岁女子长期过量喝奶茶进ICU，血糖值过高，血液呈乳白色几乎变「甜饮」，奶茶喝多少会有危险？","url":"https://www.zhihu.com/question/438403941"},{"title":"刚结婚不久，男方亲戚朋友就当着我和我婆婆面开始说：你让儿媳妇洗碗去，她不洗不做家务干嘛的。该怎么回怼？","url":"https://www.zhihu.com/question/345592311"},{"title":"如何看待特朗普称「尽管我完全不同意选举结果，但 1 月 20 日将会有序过渡」？","url":"https://www.zhihu.com/question/438312489"},{"title":"石家庄全市人员、车辆不得出市，当地疫情防控情况如何？","url":"https://www.zhihu.com/question/438325810"},{"title":"朱元璋那张鞋拔子脸的画到底是清朝抹黑还是明朝自己画的，认为这是异象？","url":"https://www.zhihu.com/question/436172958"},{"title":"如何看待伊隆·马斯克（Elon Musk）超越亚马逊创始人杰夫·贝索斯成为世界新首富？","url":"https://www.zhihu.com/question/438375132"},{"title":"2020 法考主观题出成绩了，你们考得怎么样？","url":"https://www.zhihu.com/question/438390733"},{"title":"肚子一直圆鼓鼓的，内脏脂肪要怎么减？","url":"https://www.zhihu.com/question/45723322"},{"title":"CNN 记者发布香港立法会大楼与美国国会遭遇暴力冲击的对比图，遭乱港分子围攻，对此你怎么看？","url":"https://www.zhihu.com/question/438323998"},{"title":"如何看待能在床上躺一天的舍友？","url":"https://www.zhihu.com/question/318657086"},{"title":"如何看待华信信托董事长用锤子打伤总经理被刑拘，受害人全身有 14 处伤？","url":"https://www.zhihu.com/question/438348946"},{"title":"如何看待抖音传播淫秽色情低俗信息被处罚？","url":"https://www.zhihu.com/question/438401125"},{"title":"如何评价《令人心动的offer2》第十期（大结局）？","url":"https://www.zhihu.com/question/438353764"},{"title":"《大江大河》有什么细思极恐的细节？","url":"https://www.zhihu.com/question/306141512"},{"title":"《王者荣耀》新模式守卫峡谷哪个英雄比较强势？","url":"https://www.zhihu.com/question/438159210"},{"title":"《奇葩说第七季》第五期辩题「妈妈追星不着家该阻拦吗」，你会怎么选？","url":"https://www.zhihu.com/question/438338849"},{"title":"有哪些中国书籍是永垂不朽，必须看的？","url":"https://www.zhihu.com/question/431135878"},{"title":"国会认证拜登为美国当选总统、民主党成功拿下参众两院控制权，会给美国带来哪些改变？","url":"https://www.zhihu.com/question/438303178"},{"title":"如何看待章子怡拍网剧《上阳赋》?","url":"https://www.zhihu.com/question/438267951"},{"title":"如何评价《一人之下》509（540话）?","url":"https://www.zhihu.com/question/438227762"},{"title":"老板说我设计了一周的海报还是不行，我到底该怎么学啊？","url":"https://www.zhihu.com/question/437998241"},{"title":"淘汰的 Android 手机有什么用？","url":"https://www.zhihu.com/question/26022224"},{"title":"如何看待游戏《原神》新五星角色「甘雨」？","url":"https://www.zhihu.com/question/438111372"},{"title":"如何超越牛顿、爱因斯坦，成为人类历史上最伟大的物理学家？","url":"https://www.zhihu.com/question/438277698"},{"title":"如何看待杭州一医生故意泄露流调报告内容被行拘？","url":"https://www.zhihu.com/question/438260873"},{"title":"手机游戏《原神》地图为什么中间忽然多出来个雪山?","url":"https://www.zhihu.com/question/436493509"},{"title":"有没有在高考数学中使用洛必达法则而不扣分的方法？","url":"https://www.zhihu.com/question/296821910"},{"title":"如果今年真的「就地过年」回不去家的话，你打算怎么过？怎么过年才最充实好玩？","url":"https://www.zhihu.com/question/438413078"},{"title":"如何拥有女团一般迷人的星星眼？","url":"https://www.zhihu.com/question/431143857"},{"title":"如何改变看起来木讷、不会说话、老实、性格内向的自己呢？","url":"https://www.zhihu.com/question/266384603"},{"title":"在极端寒冷天气下，你们那有哪些让南方人惊叹「还能这样」的北方玩法？","url":"https://www.zhihu.com/question/438264728"},{"title":"《奇葩说第七季》第五期有什么看点？如何评价各位选手和导师的表现？","url":"https://www.zhihu.com/question/438293386"},{"title":"为啥社会上出现开车要远离女司机的说法？","url":"https://www.zhihu.com/question/434185425"},{"title":"人到了什么年龄段才会意识到金钱的重要？","url":"https://www.zhihu.com/question/437869213"},{"title":"安西教练带队多年，为何湘北成绩一直没有起色？","url":"https://www.zhihu.com/question/28703937"},{"title":"如何看待「李娜退出中国国籍」登上微博热搜，中国驻釜山总领事馆辟谣：姓名相同？为什么会发生这种乌龙？","url":"https://www.zhihu.com/question/437901680"},{"title":"猫咪冬天是怎么取暖的？","url":"https://www.zhihu.com/question/437475353"},{"title":"到底什么材料的衣服是最保暖的？","url":"https://www.zhihu.com/question/27028959"},{"title":"小朋友三岁之前接触不到其他小朋友，三岁以后直接进幼儿园，可行吗？","url":"https://www.zhihu.com/question/430870417"},{"title":"当年勇士队的73胜，究竟是成就了勇士，还是最后成就了詹姆斯？","url":"https://www.zhihu.com/question/437796172"},{"title":"你小时候干过哪些现在看起来很沙雕的事？","url":"https://www.zhihu.com/question/437925838"},{"title":"平台强制要求外卖员买商业保险，每天交 3 元只有 1 元保费，剩下 2 元被克扣，这种操作合法吗？","url":"https://www.zhihu.com/question/438288249"},{"title":"法考大家都是怎么准备的 有什么好的备考建议或者有什么要避免的坑？","url":"https://www.zhihu.com/question/437536596"},{"title":"有哪些男主表面温润如玉实则阴狠的古言？","url":"https://www.zhihu.com/question/311422229"},{"title":"大学感觉很孤单怎么办?","url":"https://www.zhihu.com/question/434264024"},{"title":"高三了，现在分数只有300多分，我要怎样才能上550分，还有机会吗？","url":"https://www.zhihu.com/question/432904264"},{"title":"如何评价高中地理教材里的丹霞同人形象？","url":"https://www.zhihu.com/question/434559342"}]