[{"title":"看《你好，李焕英》时孩子哭得稀里哗啦，但是回家后也没多刷一个碗，说两句，还一样顶嘴，为什么呢？","url":"https://www.zhihu.com/question/444936831"},{"title":"员工实名举报中国人寿大量造假，真实情况可能是怎样的？这一现象在保险行业普遍吗？","url":"https://www.zhihu.com/question/446063707"},{"title":"如何看待人社部回应：「国内企业加班较多，不具备推行每周2.5天假期基础」？","url":"https://www.zhihu.com/question/446107907"},{"title":"看了《明朝那些事》，朱元璋农民出身应该更懂人间疾苦，为啥那么残忍？","url":"https://www.zhihu.com/question/445746439"},{"title":"如何看待年后基金大规模下跌，明星基金经理粉丝后援动摇现象，普通投资者该如何投资基金？","url":"https://www.zhihu.com/question/446059068"},{"title":"为什么我感觉有的猪肉熟了会有股刺鼻到让人想吐的臭味（不是变质的那种），但别人却感觉不到？","url":"https://www.zhihu.com/question/328620473"},{"title":"我献了400毫升血被我妈知道了，狠骂了我一顿，我想知道女生献血到底会不会对身体造成伤害？","url":"https://www.zhihu.com/question/433360504"},{"title":"为什么男生分手后很快就释怀了，女生则需要很久很久？","url":"https://www.zhihu.com/question/432503865"},{"title":"有哪些中国人觉得稀松平常，外国人无法理解的事?","url":"https://www.zhihu.com/question/435879884"},{"title":"在当今还有像钱钟书和杨绛那种灵魂伴侣吗？","url":"https://www.zhihu.com/question/445056665"},{"title":"如何看待2021年2月24号A股大跌？","url":"https://www.zhihu.com/question/446108931"},{"title":"媒体称江西永丰县残联鉴定「小马云」系二级智力残疾，可享受生活补贴、护理补贴，你怎么看待此事？","url":"https://www.zhihu.com/question/446158560"},{"title":"将时间回溯一小时（冷却时间1小时）和预知未来一小时（无冷却）之间你会选择哪种超能力？为什么？","url":"https://www.zhihu.com/question/445318653"},{"title":"如何看待上海抽检奶茶店全部存在问题，怎样保证食品卫生安全？","url":"https://www.zhihu.com/question/446069196"},{"title":"如何看待导演为《哪吒重生》着急？","url":"https://www.zhihu.com/question/445710674"},{"title":"如何看待市民举报「民警过年期间公车私用去买烤鸭」，官方回应「系处理完公务后为值班民警购买晚餐」？","url":"https://www.zhihu.com/question/445993971"},{"title":"如何看待重庆 13 岁少年擅自用压岁钱文身被武校拒收，家长要求店家担责？为什么不建议未成年文身？","url":"https://www.zhihu.com/question/445890042"},{"title":"日本制造的质量真的就那么好吗？","url":"https://www.zhihu.com/question/335156490"},{"title":"自己长得很普通，对象长得很好看怎么办?","url":"https://www.zhihu.com/question/442303033"},{"title":"如何看待2021河南省公务员考试公告及职位表？","url":"https://www.zhihu.com/question/441998633"},{"title":"如何评价《科幻世界》2021年02期银河奖征文《无主》（李卿之）全文抄袭斯蒂芬金的《重型卡车》？","url":"https://www.zhihu.com/question/446067657"},{"title":"雍正放过曾静，乾隆为什么登基之后又把曾静凌迟？","url":"https://www.zhihu.com/question/445755885"},{"title":"如果卡普、青雉、赤犬、黄猿同时邀请你做他的学生兼下属，你会选择谁？","url":"https://www.zhihu.com/question/445807112"},{"title":"恋爱中你犯过哪些错？","url":"https://www.zhihu.com/question/439563652"},{"title":"鞠婧祎的眼妆是怎么画的?","url":"https://www.zhihu.com/question/303394696"},{"title":"有失望至极的句子吗？","url":"https://www.zhihu.com/question/339068772"},{"title":"第一次去女朋友家，拿什么东西合适？需要很昂贵吗？","url":"https://www.zhihu.com/question/335168600"},{"title":"你敢用一年时间改变自己吗？","url":"https://www.zhihu.com/question/437098355"},{"title":"如何评价张艺谋导演的《长城》？","url":"https://www.zhihu.com/question/319452692"},{"title":"考研人数逐年递增，你为什么选择考研？是什么让你坚定了考研的决心？","url":"https://www.zhihu.com/question/445892304"},{"title":"烘干机使用一年后你还会封阳台吗？烘干机一年或几个月的使用感怎样?","url":"https://www.zhihu.com/question/426305815"},{"title":"2 月 25 日早上滴滴崩了，你上班迟到了吗？有哪些替代 App？","url":"https://www.zhihu.com/question/446246909"},{"title":"分手了，有必要做朋友吗？","url":"https://www.zhihu.com/question/445595249"},{"title":"当老师进入教室发现黑板没擦，老师该怎么做最好？","url":"https://www.zhihu.com/question/439153083"},{"title":"如何看待男子请求武汉政府「分配对象」被拒，婚恋难已成为普遍的社会问题了吗？","url":"https://www.zhihu.com/question/446131446"},{"title":"阿迪达斯旗下都有哪些系列鞋款？","url":"https://www.zhihu.com/question/28145748"},{"title":"不是很熟的同学跟你借钱，你会借吗？","url":"https://www.zhihu.com/question/445561963"},{"title":"刘雨昕有什么样的魅力，为什么那么多人喜欢她？","url":"https://www.zhihu.com/question/429215902"},{"title":"如何看待将于2月23日发布的奔驰全新C级，动力系统将全系电气化？","url":"https://www.zhihu.com/question/445393919"},{"title":"有那些好习惯需要养成？","url":"https://www.zhihu.com/question/431242009"},{"title":"新手老师怎么做才能不凶学生又能管住学生？","url":"https://www.zhihu.com/question/429786632"},{"title":"如何看待杨超越代言麦当劳「轻盈夏巴特」系列？","url":"https://www.zhihu.com/question/445911384"},{"title":"请问怎么才能忘记一个人？","url":"https://www.zhihu.com/question/441669768"},{"title":"在眼镜发明之前，近视了的人是怎样生活的？","url":"https://www.zhihu.com/question/20057134"},{"title":"历经8年，成功让近1亿贫困人口实现脱贫。中国的「战贫之路」到底有多艰难？","url":"https://www.zhihu.com/question/446159337"},{"title":"哪一秒你觉得合租真难受？","url":"https://www.zhihu.com/question/294243719"},{"title":"张伯礼称三月初是国内疫情拐点，年底有望恢复到疫情前状态，你有哪些期待？","url":"https://www.zhihu.com/question/446090361"},{"title":"为什么游戏公司总是不愿意出面解释自己的决策？","url":"https://www.zhihu.com/question/445577735"},{"title":"为什么现在总鼓励年轻人正面刚？","url":"https://www.zhihu.com/question/440608876"},{"title":"人们看电影的意义是什么？","url":"https://www.zhihu.com/question/27933396"}]