[{"title":"东航一架波音 737 客机在广西藤县坠毁，机上 132 人伤亡未明，情况如何？可能是什么原因造成的？","url":"https://www.zhihu.com/question/523245532"},{"title":"2022 年中国是否有可能开放入境?","url":"https://www.zhihu.com/question/517046242"},{"title":"如何看待今麦郎被质疑是日资企业，再度发声称「百分百民营企业，没有一分钱外资」？这反映了什么现象？","url":"https://www.zhihu.com/question/523036517"},{"title":"秦刚做客美电视节目遭「区别对待」，9 分钟被打断 23 次，该主持是何意图？","url":"https://www.zhihu.com/question/523221016"},{"title":"东航一客机在广西确认坠毁，138 名消防救援人员已赶赴现场，目前情况如何？搜救难度有多大？","url":"https://www.zhihu.com/question/523262879"},{"title":"你怎么看女子卖了4套房创业12年如今负债1亿？","url":"https://www.zhihu.com/question/522655328"},{"title":"施一公直播回应西湖大学本科专业多「天坑」，建议学生和家长不要过多关注收入和就业，你怎么看？","url":"https://www.zhihu.com/question/523109683"},{"title":"在英中国女留学生失联 19 天，其父称最近一次视频通话是在 3 月 1 日晚上，目前已找到，情况如何？","url":"https://www.zhihu.com/question/523051267"},{"title":"男朋友说蝙蝠侠是一个父母死了穿着蝙蝠衣到处泄愤的疯子，我该怎么反驳他？","url":"https://www.zhihu.com/question/402950168"},{"title":"中方向乌克兰新增 1000 万元人道主义援助，可以给当地哪些帮助？","url":"https://www.zhihu.com/question/523239542"},{"title":"网友称在盒马花 1888 元买到整条活鳄鱼，盒马回应称「商品为冷冻品」，吃人工鳄鱼犯法吗？","url":"https://www.zhihu.com/question/523041503"},{"title":"为什么美国侵略别国就不叫侵略，俄罗斯打击乌克兰就叫侵略？有什么不一样吗？","url":"https://www.zhihu.com/question/521818786"},{"title":"如何看待哈尔滨工程大学禁止英语六级刷分「已过六级者不可再次报考，学生不得连续报考六级」？","url":"https://www.zhihu.com/question/522635113"},{"title":"专家称「 60 岁退休是劳动力和智力上的社会资源浪费」，如何评价这一观点？","url":"https://www.zhihu.com/question/523205425"},{"title":"如何看待小米副总裁卢伟冰吐槽手机行业双标，现在手机圈双标现象有多严重？","url":"https://www.zhihu.com/question/432220305"},{"title":"22考研国家线已出，大概300W考生没有上岸，他们该何去何从？","url":"https://www.zhihu.com/question/521697296"},{"title":"乐事薯片或将从 4 月 15 日开始涨价，你能接受吗？涨价可能出于哪些原因考虑？","url":"https://www.zhihu.com/question/523209098"},{"title":"单休6200双休5000怎么选？","url":"https://www.zhihu.com/question/495480947"},{"title":"如何看待 「中国女孩年级第一牛津毕业被质疑」这一事件？","url":"https://www.zhihu.com/question/522700465"},{"title":"《楚门的世界》中，妻子既然不爱楚门为什么反复提及要与楚门生一个孩子？","url":"https://www.zhihu.com/question/305864895"},{"title":"为什么大陆演员很难演出香港黑帮片中的那种骨子里的江湖气？","url":"https://www.zhihu.com/question/480849535"},{"title":"如何看待江西财经大学核酸检测直到凌晨四点半才结束？期间安排是否合理？","url":"https://www.zhihu.com/question/522661192"},{"title":"如何看待韩国候任总统尹锡悦宣布将总统办公室迁出青瓦台？这意味着什么？","url":"https://www.zhihu.com/question/523053579"},{"title":"哪个瞬间你突然觉得读书真有用？","url":"https://www.zhihu.com/question/35720340"},{"title":"白宫官员称「美国可能扩大对俄制裁，涉及更多银行和部门」，有哪些信息值得关注？","url":"https://www.zhihu.com/question/523222763"},{"title":"3 月 21 日是世界睡眠日，很多人都会出现睡眠困难，有哪些高质量的睡眠攻略吗？","url":"https://www.zhihu.com/question/523221315"},{"title":"与导师汇报学习进度的时候没东西写，就只是看了几篇文献，该怎么办？","url":"https://www.zhihu.com/question/434614589"},{"title":"魂系列、只狼、艾尔登法环等 FROMSOFTWARE 游戏中的平民百姓都去哪了？","url":"https://www.zhihu.com/question/522796536"},{"title":"象棋里的车是不是过强级了？是否应该削弱一下?","url":"https://www.zhihu.com/question/426985535"},{"title":"怎么判断孩子是不是学霸的料？","url":"https://www.zhihu.com/question/487414207"},{"title":"女朋友生日该送什么礼物？","url":"https://www.zhihu.com/question/268196841"},{"title":"画画时，如何准确的起形？","url":"https://www.zhihu.com/question/21292233"},{"title":"长春有哪些春天的时令美食，适合在春天「尝第一口鲜」？","url":"https://www.zhihu.com/question/523154048"},{"title":"为什么现在招聘C++程序员这么难？","url":"https://www.zhihu.com/question/491876804"},{"title":"考驾照哪科最难?","url":"https://www.zhihu.com/question/522040424"},{"title":"一直不谈恋爱真的会等到很好的人嘛？","url":"https://www.zhihu.com/question/523214483"},{"title":"女生努力工作，担任重要岗位，然而领导并没有什么认可，工资完全低于自我预期，怎么办呢？","url":"https://www.zhihu.com/question/517104374"},{"title":"抑郁症失去兴趣很久了，最近突然对打游戏很感兴趣，我应该坚持吗？","url":"https://www.zhihu.com/question/512413459"},{"title":"PMP 考试一定要报培训班吗？","url":"https://www.zhihu.com/question/280509086"},{"title":"当面临读书还是打工的时候，该怎么选？","url":"https://www.zhihu.com/question/521875273"},{"title":"山东援威专家 80 后博导白晓卉抗疫中因心梗去世，你有什么想说的？还有哪些抗疫英雄值得我们致敬?","url":"https://www.zhihu.com/question/523045302"},{"title":"如何看待卢伟冰说 K50 已经实现局部超越 iPhone，友商也要加油超越苹果？","url":"https://www.zhihu.com/question/522527489"},{"title":"为什么轻奢品牌的衣服那么贵？","url":"https://www.zhihu.com/question/514852754"},{"title":"游戏《艾尔登法环》中有哪些乍一看没什么，细想想却很可悲的设定？","url":"https://www.zhihu.com/question/518457201"},{"title":"3 月 20 日 31 个省区市新增本土确诊 1947 例，无症状感染者 2384 例，各地情况如何？","url":"https://www.zhihu.com/question/523168816"},{"title":"之前一直用华为，3000 左右的手机请问有什么推荐吗 ？","url":"https://www.zhihu.com/question/522205150"},{"title":"为什么很多人的梦想都是环游世界？","url":"https://www.zhihu.com/question/516473737"},{"title":"为什么旅行路上会感觉「去途远，归途近」呢？","url":"https://www.zhihu.com/question/520140245"},{"title":"对《海贼王》漫画 1044 话情报有何预测？","url":"https://www.zhihu.com/question/522909928"},{"title":"《艾尔登法环》都有哪些粪怪，如何应对？","url":"https://www.zhihu.com/question/522074978"}]