[{"title":"浙江、四川、南京等地多人确诊热射病，已有死亡病例，热射病是怎么回事？如何预防与治疗？","url":"https://www.zhihu.com/question/542910685"},{"title":"如何看待打假人王海称「18 元钟薛高成本仅 1.32 元」？若属实钟薛高定价是否合理？","url":"https://www.zhihu.com/question/542909123"},{"title":"7 月 13 日美舰再次擅闯中国西沙领海，南部战区组织兵力进行跟踪监视并警告驱离，释放了哪些信号？","url":"https://www.zhihu.com/question/543047625"},{"title":"多地提高医保最低缴费年限，男 30 年女 25 年，这透露出了哪些信号？","url":"https://www.zhihu.com/question/542824861"},{"title":"推特正式起诉马斯克，迫使其完成 440 亿美元对推特的收购，案件后续会如何发展？推特胜诉可能性大吗？","url":"https://www.zhihu.com/question/543000090"},{"title":"《乘风破浪》于文文组演绎歌曲《佳人》，全员旗袍造型，你觉得好看吗？褪去舞台光环，现实中怎么穿好旗袍？","url":"https://www.zhihu.com/question/541416568"},{"title":"蓝条是不是已经成为《英雄联盟》里可有可无的设定了？","url":"https://www.zhihu.com/question/541482588"},{"title":"为什么都说「土到极致就是潮」？有哪些土成功的例子？","url":"https://www.zhihu.com/question/295264922"},{"title":"今年油价上涨，我把汽油标号降低一个等级，对车有什么伤害？","url":"https://www.zhihu.com/question/522436063"},{"title":"如何看待乐视回应员工躺平，称「公司没有 996，没有拖欠过员工工资和社保」，乐视目前主要靠什么盈利？","url":"https://www.zhihu.com/question/542904601"},{"title":"三岁看大，七岁看老的底层逻辑在哪里？","url":"https://www.zhihu.com/question/536558450"},{"title":"如何看待茶卡盐湖旅游集散中心距景区 5 公里，游客必须坐摆渡车，每人 30 元，景区回应未参与收费？","url":"https://www.zhihu.com/question/542542268"},{"title":"东莞楼市新政发布一周，有楼盘推出 0.5 成首付，有售楼处拉横幅热烈欢迎深圳购房团，哪些信息值得关注？","url":"https://www.zhihu.com/question/543013301"},{"title":"媒体报道尼康否认宣布退出单反相机的开发，将继续生产、销售和支持数码单反相机，具体情况如何？","url":"https://www.zhihu.com/question/542916457"},{"title":"如何看待乌克兰任命 25 岁的安娜·谢尔盖耶娃为乌克兰欧洲一体化事务的副部长？她能否胜任该职位？","url":"https://www.zhihu.com/question/542841758"},{"title":"国务院联防联控机制表示「不再对进口非冷链物品核酸检测」，如何看待这一举措？对相关行业有哪些影响？","url":"https://www.zhihu.com/question/542934654"},{"title":"《原神》2.8 版本「仲夏！幻夜？奇想曲！」更新，你的体验如何？","url":"https://www.zhihu.com/question/543036594"},{"title":"7 月 12 日河南新增本土「3+22」，在驻马店、郑州，目前当地疫情情况如何？","url":"https://www.zhihu.com/question/543004377"},{"title":"你们家乡有哪些很特别的水果？","url":"https://www.zhihu.com/question/502267358"},{"title":"网传疑似上海中考数学某试题泄题，上海市教育考试院回应「已报案」，具体情况如何？","url":"https://www.zhihu.com/question/542935293"},{"title":"住青旅的时候，男女混住是一种什么样的体验？","url":"https://www.zhihu.com/question/65728703"},{"title":"新东方辞退拒绝调岗员工被判赔 38.25 万元，如何从法律角度解读此判决？","url":"https://www.zhihu.com/question/542876018"},{"title":"腕表与汽车界有哪些惊人的巧合？","url":"https://www.zhihu.com/question/542725914"},{"title":"泽连斯基提交给予波兰人「特殊地位」法案，被批「正式向波移交领土」，他为何这么做？后续将如何发展？","url":"https://www.zhihu.com/question/542929870"},{"title":"夏天来了，你最想去哪个地方避暑呢？","url":"https://www.zhihu.com/question/470842582"},{"title":"斯里兰卡处于国家崩溃的边缘，他的人民应该何去何从?","url":"https://www.zhihu.com/question/542653182"},{"title":"成都2022.7.12号二批次土拍第一天上午就5宗熔断摇号，是否说明成都未来两三年房价是不会再跌了?","url":"https://www.zhihu.com/question/542859060"},{"title":"本硕都是中文系，进了公务员体制就是写稿子吗？","url":"https://www.zhihu.com/question/541102917"},{"title":"《原神》2.8 版本抽万叶还是等 3.0 版本的草神？","url":"https://www.zhihu.com/question/538997348"},{"title":"全球人口增速达到了 1950 年以来的最低水平，其原因可能为何？人口增速下降将带来哪些影响？","url":"https://www.zhihu.com/question/542821678"},{"title":"如何看待韩国女主播玩《英雄联盟》被恶意击杀 121 次，并遭举报封号？","url":"https://www.zhihu.com/question/542731467"},{"title":"如何评价藤本树漫画《电锯人》第二部第一话？","url":"https://www.zhihu.com/question/542912527"},{"title":"杨槠策给余秀华手写道歉信曝光，该信有多处错字，信中称「对自己的家暴行为感到恶心」，如何看待这件事？","url":"https://www.zhihu.com/question/542897478"},{"title":"暑假打算带上女朋友去广州玩四五天，都有哪些攻略？","url":"https://www.zhihu.com/question/525297624"},{"title":"山西太原一名女子火车上遭男子猥亵装睡冷静取证，该男子将面临怎样的法律责任？","url":"https://www.zhihu.com/question/542808549"},{"title":"怎样做一名高效率程序员？","url":"https://www.zhihu.com/question/433233218"},{"title":"如何评价木心？","url":"https://www.zhihu.com/question/20492929"},{"title":"中方回应斯里兰卡涉华债务，称支持有关金融机构同斯方协商，寻求妥善解决，有哪些信息值得关注？","url":"https://www.zhihu.com/question/542929951"},{"title":"电视剧《士兵突击》中，为什么许三多说帮助自己最多的人是袁朗，而不是史今？","url":"https://www.zhihu.com/question/268095301"},{"title":"白宫预计 6 月通胀处高位，美元徘徊二十年高位，美股尾盘跳水，纳指跌近 1%，美国还面临哪些经济问题？","url":"https://www.zhihu.com/question/543004546"},{"title":"网传上海航班全部取消，机场回复为「假消息」，真实情况如何？全国进入暑运旺季，各地航班恢复情况如何？","url":"https://www.zhihu.com/question/543040171"},{"title":"印度央行推出国际贸易卢比结算机制 ，该机制都有哪些值得关注的亮点？","url":"https://www.zhihu.com/question/542911309"},{"title":"高考完想去西藏，有什么旅行建议和注意事项？","url":"https://www.zhihu.com/question/530354008"},{"title":"提名程序结束，英国 8 名保守党成员参与党首角逐，谁有望最终胜出？对英国政坛将产生哪些影响？","url":"https://www.zhihu.com/question/543033731"},{"title":"2022 年上半年我国货物贸易进出口总值 19.8 万亿元，同比增长 9.4 %，如何解读？","url":"https://www.zhihu.com/question/543025261"},{"title":"第七批国家药品集采拟中选产品 327 个，药品集采平均降价 48%，这对患者提供了什么保障？","url":"https://www.zhihu.com/question/542935335"},{"title":"有哪些小众且惊艳诗词?","url":"https://www.zhihu.com/question/532105064"},{"title":"有人今年去读本科助学班吗？","url":"https://www.zhihu.com/question/542931651"},{"title":"进入社会以后，人情世故真的很重要吗？","url":"https://www.zhihu.com/question/542844203"},{"title":"高三最后一年看不到希望了怎么办?","url":"https://www.zhihu.com/question/542741109"}]