[{"title":"《我的县长父亲》获征文一等奖后遭删除，如何从文学角度分析这一文章水平？","url":"https://www.zhihu.com/question/554365776"},{"title":"浙江义乌要求商家下架槟榔，当地市监局称接上级通知，永久性禁售槟榔，吃槟榔对人体有哪些危害？","url":"https://www.zhihu.com/question/554405669"},{"title":"如何看待联邦快递崩了还警告「全球衰退」？","url":"https://www.zhihu.com/question/554251604"},{"title":"德国州长称「北溪 2 号永远不会投入运营」，如何看待其表态？德国可能摆脱对俄的能源依赖吗？","url":"https://www.zhihu.com/question/554392897"},{"title":"为什么食肉动物不互相eat呢？","url":"https://www.zhihu.com/question/546078439"},{"title":"同事离职请了大家吃饭，唯独没叫我，平时关系不错，想不通，我应该纠结心塞吗？怎么缓解心情？","url":"https://www.zhihu.com/question/539307553"},{"title":"罗永浩批苹果灵动岛宣传视频造假，称真机很丑，如何评价苹果的灵动岛设计？","url":"https://www.zhihu.com/question/554369068"},{"title":"为什么宋江宁愿杀了阎婆惜也不愿满足她的要求?","url":"https://www.zhihu.com/question/554059663"},{"title":"世界上第一辆飞行自行车亮相，可飞 40 分钟，预售价约为 77.7 万美元，你对该产品有哪些期待？","url":"https://www.zhihu.com/question/554208054"},{"title":"敷尔佳 148 元一盒面膜成本仅 10 元，面膜类化妆品的普遍成本是多少？为什么面膜产品如此暴利？","url":"https://www.zhihu.com/question/554359229"},{"title":"贵阳三名干部因三荔高速重大交通事故被组织处理，这起到了哪些警示作用？","url":"https://www.zhihu.com/question/554387184"},{"title":"一人一天能走9万多步吗？","url":"https://www.zhihu.com/question/328957067"},{"title":"美军电子侦察机在黄、东海进行高强度抵近侦察，这释放了哪些信息？","url":"https://www.zhihu.com/question/554339494"},{"title":"俄媒称「俄遭制裁后仅有150家外企撤出当地市场，占比0.6%」，如何解读这一数据？","url":"https://www.zhihu.com/question/554348630"},{"title":"如何看待《我的县长父亲》作者发声称最初的题目叫《逝去的背影》，只想实事求是地讲父亲的故事？","url":"https://www.zhihu.com/question/554390998"},{"title":"现在买新手机不买 5G 的话，以后会有哪些必须依赖 5G 的实用功能跟不上吗？","url":"https://www.zhihu.com/question/553399508"},{"title":"敢不敢晒婆婆做的月子餐？","url":"https://www.zhihu.com/question/347580647"},{"title":"既然中国自古以来也酿葡萄酒，为什么没有形成像西餐一样的葡萄酒佐餐文化？","url":"https://www.zhihu.com/question/551937274"},{"title":"重庆猴痘病例病毒与德国病毒高度同源，有哪些信息值得关注？生活中应如何防护？","url":"https://www.zhihu.com/question/554352414"},{"title":"姚明在《灌篮高手》里大概是什么水平？","url":"https://www.zhihu.com/question/342229897"},{"title":"我现在快40了，想写小说，会不会太迟了？会有出路吗？","url":"https://www.zhihu.com/question/545207849"},{"title":"为什么文丑的名字要叫“丑”?","url":"https://www.zhihu.com/question/551390638"},{"title":"国家发改委表示「今后几个月重点防范生猪价格过快上涨」，释放了怎样的信号？","url":"https://www.zhihu.com/question/554333715"},{"title":"日媒称日本总和生育率跌至 1.30 创新低，未来日本或不复存在，如何看待此评论？日本如何应对人口危机？","url":"https://www.zhihu.com/question/553578475"},{"title":"郭靖黄蓉结婚后，黄老邪为何离家出走，放弃了整个桃花岛？","url":"https://www.zhihu.com/question/536798107"},{"title":"宝宝鞋子怎么选？不同阶段有什么讲究吗？","url":"https://www.zhihu.com/question/482732430"},{"title":"高中友谊重要还是学习重要？","url":"https://www.zhihu.com/question/548326176"},{"title":"你们开始学Pr的时候，都怎么学的?","url":"https://www.zhihu.com/question/335038113"},{"title":"三体那么好，为什么刘慈欣得不到诺贝尔文学奖？","url":"https://www.zhihu.com/question/554068601"},{"title":"乌克兰国家核电公司称南乌克兰核电站遭导弹袭击，有哪些信息值得关注？","url":"https://www.zhihu.com/question/554365442"},{"title":"处理器只能做到64位，而软件越来越臃肿，会不会有一天出现寻址能力不够一个软件使用的情况？","url":"https://www.zhihu.com/question/504238985"},{"title":"长沙某饮品店制作饮品时未按顾客要求去冰，顾客直接将饮品倒在操作台上，双方是否有更好的处理方法？","url":"https://www.zhihu.com/question/554326875"},{"title":"为什么人无法忍受40℃的环境温度，在40℃的水里却很滋润？","url":"https://www.zhihu.com/question/67357858"},{"title":"C++之父本人自己写的C++教材，为何并不是最受欢迎的教材？","url":"https://www.zhihu.com/question/550407460"},{"title":"虎牙《英雄联盟》主播姿态和水晶哥同时宣布停播，发生了什么？","url":"https://www.zhihu.com/question/552036859"},{"title":"俄媒称「德总理认为，尽管双方意见南辕北辙，但必须进一步与俄总统普京进行对话」，这释放出哪些信号？","url":"https://www.zhihu.com/question/554364848"},{"title":"如何看待 9 月 19 日股市再次下跌，上证指数一度险些失守 3100 点？","url":"https://www.zhihu.com/question/554358919"},{"title":"北京时间 20 日墨西哥发生 7.7 级地震，多地发布海啸预警，已造成 1 人死亡，目前情况如何？","url":"https://www.zhihu.com/question/554428730"},{"title":"《英雄联盟》为什么没有坦克型刺客？","url":"https://www.zhihu.com/question/553985220"},{"title":"狼人杀为什么禁止贴脸？","url":"https://www.zhihu.com/question/462970840"},{"title":"《风云》里，雄霸如果没有收风云为徒，凭他自己难道就统一不了江湖吗？","url":"https://www.zhihu.com/question/531165188"},{"title":"《原神》中，如果你只能用10个五星（旅行者除外），你会带上谁？","url":"https://www.zhihu.com/question/554092036"},{"title":"美元指数今年来飙升 14%，美媒警告「将给全球经济带来大麻烦」，如何解读？美元走强会引发哪些问题？","url":"https://www.zhihu.com/question/554366266"},{"title":"如何看待《柳叶刀》杂志新冠委员会主席称「Covid-19 可能起源于美国生物实验室」？有哪些值得关注？","url":"https://www.zhihu.com/question/541154437"},{"title":"央行发布 2022 年 9 月 LPR 维持不变，对我国经济有何影响？","url":"https://www.zhihu.com/question/554439413"},{"title":"如何评价《英雄联盟》电竞选手 Doinb 举办的 LBL 赛事？","url":"https://www.zhihu.com/question/553960226"},{"title":"「洗米华」案开审，其被控触犯 289 项罪名，非法投注金额约 6800 亿人民币，哪些信息值得关注？","url":"https://www.zhihu.com/question/538985026"},{"title":"奥地利爆发超 3.2 万人大游行，抗议政府解决生活成本危机不力，后续将如何发展？","url":"https://www.zhihu.com/question/554284748"},{"title":"Node.js 有哪些设计缺陷？","url":"https://www.zhihu.com/question/551760588"},{"title":"本人想买个便宜点的轻薄办公笔记本，有什么本子值得买？","url":"https://www.zhihu.com/question/425534566"}]