[{"title":"「天价月饼」出新招，标价 499 元运费 600 元，发改委已出手整治，遏制高价月饼将带来哪些改变？","url":"https://www.zhihu.com/question/550203746"},{"title":"一种新水果诞生，中国科学家历时 15 年培养出「脆蜜」，是龙眼+荔枝的后代，这一成就具有哪些意义？","url":"https://www.zhihu.com/question/550203685"},{"title":"网传某公司要求一旦怀孕自动离职，如何从法律角度解读该事件？企业生育歧视背后的根源在哪里？","url":"https://www.zhihu.com/question/550341166"},{"title":"美国社交媒体集体宣布「删除部分亲美虚假账号」，该行动有何值得关注的信息？","url":"https://www.zhihu.com/question/550268256"},{"title":"有什么动物长得人畜无害的其实杀伤力爆表？","url":"https://www.zhihu.com/question/310860753"},{"title":"如何看待库克称「苹果的长期目标是不必用地球上的任何资源来制造产品」？","url":"https://www.zhihu.com/question/550119471"},{"title":"青岛一小区内人工湖中发现多条外来物种鳄雀鳝，物业抽干湖水抓捕 ，鳄雀鳝对当地生态有哪些影响？","url":"https://www.zhihu.com/question/550274141"},{"title":"如果《英雄联盟》有一个英雄没有技能，但有全游最高基础属性，他强度怎么样？","url":"https://www.zhihu.com/question/538818349"},{"title":"贵州黄平事业单位招聘笔试出现断崖式分差，11 人因作弊被取消成绩，他们将面临哪些处罚？","url":"https://www.zhihu.com/question/550280622"},{"title":"19 岁男子偷玛莎拉蒂从长沙开到九江，被判 10 年罚 5 万，如何从法律角度解读此判罚？","url":"https://www.zhihu.com/question/550226342"},{"title":"给你3000万或3000万个忠诚的朋友 你选哪一个？","url":"https://www.zhihu.com/question/546903618"},{"title":"鄱阳湖干旱 40天 缩水 69%，政府拟投资 435 亿建 2331 个水利项目，现当地情况如何？","url":"https://www.zhihu.com/question/550276153"},{"title":"陕西榆林一夫妇卖 5 斤芹菜被罚 6.6 万，当地处罚过当被督查，如何从法律角度解读？","url":"https://www.zhihu.com/question/550270325"},{"title":"价格标签失踪、一支中性笔卖 55 元，如何看待这种「文具刺客」现象？你被刺到了吗？","url":"https://www.zhihu.com/question/550370662"},{"title":"读那种看似名著的小说有什么特别意义？","url":"https://www.zhihu.com/question/365872692"},{"title":"如何看待歼-20 、歼-16 和歼-10C 登上最新的小学生《科学》教科书封面？","url":"https://www.zhihu.com/question/549784530"},{"title":"湘雅二院刘翔峰被查，中纪委网站发声「坚决维护医疗领域风清气正」，该事件起到了哪些警示作用?","url":"https://www.zhihu.com/question/550357370"},{"title":"台媒称「疑似大陆无人机进入小金门台军据点拍摄」，这透露出什么信息？还有哪些信息值得关注？","url":"https://www.zhihu.com/question/550382142"},{"title":"普京宣布十年来最大规模扩军计划，为何俄罗斯逐步从裁军走向了扩军？这一变化会影响其它国家的军事战略吗？","url":"https://www.zhihu.com/question/550291630"},{"title":"如何看待美国警告俄罗斯勿转移札波罗热核电厂电力？","url":"https://www.zhihu.com/question/550246544"},{"title":"如何看待长安汽车董事长称「中国汽车产业已初具停售燃油车基本条件」？燃油车退出会给汽车行业造成哪些影响？","url":"https://www.zhihu.com/question/550260331"},{"title":"9 岁男孩反复发烧，「开学综合征」患儿扎堆就诊，为何会出现这一状况？该如何缓解？","url":"https://www.zhihu.com/question/550346370"},{"title":"猫咪对小孩子真的下不去爪子吗?","url":"https://www.zhihu.com/question/365731507"},{"title":"首尔一高中因生源不足即将关闭，韩国空置中小学校已达 1400 多所，韩国学龄人口减少原因是什么？","url":"https://www.zhihu.com/question/550301505"},{"title":"俄专家称这不会是俄罗斯的最后一次扩军，如何理解这一观点？俄罗斯军队人数会持续增加吗？","url":"https://www.zhihu.com/question/550284111"},{"title":"如何评价美军方炒作称，中国想于 2045 年取代美国「称霸」太空？如今中国航天处于什么水平？","url":"https://www.zhihu.com/question/550368354"},{"title":"恐怖型的真人密室逃脱有多可怕？","url":"https://www.zhihu.com/question/323305030"},{"title":"22-23 赛季英超曼城 4:2 水晶宫，如何评价这场比赛？","url":"https://www.zhihu.com/question/550298626"},{"title":"云南人吃野生菌有哪些迷惑行为？","url":"https://www.zhihu.com/question/541660164"},{"title":"为什么不写一个万能的什么都能干的shader?","url":"https://www.zhihu.com/question/424299418"},{"title":"如果A10放到二战会不会变成最强的战斗机?（只能使用机炮，不能用aam）?","url":"https://www.zhihu.com/question/547623851"},{"title":"我高中没考上，我要去打工吗？","url":"https://www.zhihu.com/question/550246052"},{"title":"看电视剧和看书，哪个对人提升有帮助？","url":"https://www.zhihu.com/question/546260835"},{"title":"法国电价一年涨了 11 倍，英国户均能源账单或升至一年 4188 英镑，如何看待欧洲能源危机持续恶化？","url":"https://www.zhihu.com/question/550261436"},{"title":"为什么麦林炮手的登场率这么低？","url":"https://www.zhihu.com/question/372193263"},{"title":"为什么还有人用VIM？","url":"https://www.zhihu.com/question/547708456"},{"title":"为什么旅行者在璃月之后去稻妻而不是须弥？","url":"https://www.zhihu.com/question/549881794"},{"title":"计算机直博毕业要求两篇顶会一作难度如何？","url":"https://www.zhihu.com/question/546807912"},{"title":"租一辈子房会不会后悔？","url":"https://www.zhihu.com/question/22100326"},{"title":"大疆为什么不做油动无人机？","url":"https://www.zhihu.com/question/549907308"},{"title":"为什么电脑城总喜欢给电脑装盗版系统，明知品牌整机内置正版了?","url":"https://www.zhihu.com/question/526769152"},{"title":"装修小白即将开始装修房子，要注意些什么？","url":"https://www.zhihu.com/question/368485703"},{"title":"如何评价《这！就是街舞》第五季第三期？","url":"https://www.zhihu.com/question/550232243"},{"title":"有哪个瞬间让你觉得这个世界出bug了？","url":"https://www.zhihu.com/question/278294552"},{"title":"反社会人格有哪些不可思议的行为？","url":"https://www.zhihu.com/question/35079273"},{"title":"你见过哪些父母惊艳到你的教育方式？","url":"https://www.zhihu.com/question/264918610"},{"title":"准大一新生应该买电脑还是平板？","url":"https://www.zhihu.com/question/547038953"},{"title":"江苏一女子吃霸王餐被拦下后踢打店员，父母赶来替其付款称女子有抑郁症。如何看待该女子的行为？","url":"https://www.zhihu.com/question/550123933"},{"title":"对于孩子不喜欢吃的东西，应该采取怎样的态度去应对？家长一定要逼着孩子吃吗？","url":"https://www.zhihu.com/question/547159026"},{"title":"你觉得读书有什么意义?","url":"https://www.zhihu.com/question/549947480"}]