[{"title":"《黑神话：悟空》8 月 20 日实机剧情片段与 GeForce 独家实机试玩中，有哪些值得关注的信息？","url":"https://www.zhihu.com/question/549196095"},{"title":"如何看待美国一大学生炒股，一个月内赚了 1.1 亿美元？","url":"https://www.zhihu.com/question/549069715"},{"title":"为什么日本海鱼可以做顶级刺身，而中国的海鱼却大多做熟?","url":"https://www.zhihu.com/question/548875804"},{"title":"刚刚学到了如月千早这个「成语」，感觉大受震撼，请问类似的成语还有什么呢？","url":"https://www.zhihu.com/question/548778171"},{"title":"亚开行行长称「明年将讨论结束对中国的贷款」，这意味着什么？可能对我国带来哪些影响？","url":"https://www.zhihu.com/question/549116732"},{"title":"中国最大淡水湖「缩水」退至同期最低水位 9.99 米，可能是哪些因素造成的？会带来哪些影响？","url":"https://www.zhihu.com/question/549183665"},{"title":"14岁了还是没有自己的房间很难受怎么办?","url":"https://www.zhihu.com/question/539432920"},{"title":"中国的芯片工业水平能否在10年内达到世界前列呢？","url":"https://www.zhihu.com/question/543811431"},{"title":"如果我不小心得到了李白所有失传的诗歌，然后学范闲，以我的名义在网上发布怎么样？","url":"https://www.zhihu.com/question/548148644"},{"title":"甘肃瓜州县卫健局长石金龙在疫情防控中因公殉职，英年 51 岁，他的哪些精神值得我们铭记？","url":"https://www.zhihu.com/question/549193059"},{"title":"如何评价曾被批「回车键分行写作」的贾平凹之女贾浅浅入围中国作家协会会员名单？贾浅浅的诗真实水平如何？","url":"https://www.zhihu.com/question/548935730"},{"title":"广东一妈妈在网络平台分享妊娠纹视频，却遭到平台限流甚至屏蔽，对此你怎么看？","url":"https://www.zhihu.com/question/548942800"},{"title":"为了吃掉碗中最后一粒米所消耗的能量和这粒米所能提供的能量哪个多？","url":"https://www.zhihu.com/question/329670270"},{"title":"「葡萄中的爱马仕」阳光玫瑰葡萄价格从「百元档」掉入「十元档」，为什么会出现这样的情况？","url":"https://www.zhihu.com/question/549207620"},{"title":"为什么所有人都在告诉我好好学习？","url":"https://www.zhihu.com/question/459911403"},{"title":"中式恐怖元素有哪些？","url":"https://www.zhihu.com/question/401235094"},{"title":"特朗普共和党内「头号敌人」在初选中落败，透露出哪些信息？美国党争局势如何？","url":"https://www.zhihu.com/question/548986699"},{"title":"为啥银行就这么不愿意让我提前还贷？","url":"https://www.zhihu.com/question/548762567"},{"title":"如何评价综艺《中国说唱巅峰对决》第九期？","url":"https://www.zhihu.com/question/549210525"},{"title":"美国疾病控制与预防中心承认疫情防控失误，将展开全面重组，会有哪些措施出台，将产生什么影响？","url":"https://www.zhihu.com/question/549102295"},{"title":"8 月 19 日美国「里根号」航母返回日本横须贺母港，这意味着什么？","url":"https://www.zhihu.com/question/549066791"},{"title":"《原神》如何忍住不抽，攒起原石？","url":"https://www.zhihu.com/question/548977042"},{"title":"对于第一次去新疆旅游的人，你有哪些建议？","url":"https://www.zhihu.com/question/535528786"},{"title":"打完俄罗斯的乌克兰还有未来吗?","url":"https://www.zhihu.com/question/547578221"},{"title":"河南成为全国第一个所有县市国家站都有过 40 度高温的省份，高温天气下我们该如何降温防暑？","url":"https://www.zhihu.com/question/549170429"},{"title":"电影《黑社会》里选话事人为什么不贿赂邓伯？","url":"https://www.zhihu.com/question/544806310"},{"title":"英语这种毫无规律的语言是怎么被造出来的？","url":"https://www.zhihu.com/question/523005869"},{"title":"我初二学习300多分，还能逆袭吗？","url":"https://www.zhihu.com/question/549226541"},{"title":"我开学就高二了可是学习很差，上个普通高中也是靠关系上的，如果我想考个好点的大学还有希望吗?","url":"https://www.zhihu.com/question/549178339"},{"title":"一个人独自去旅行是什么感受?","url":"https://www.zhihu.com/question/349215851"},{"title":"有报告称人工智能业人才紧缺，算法工程师应届生平均月薪超 3.2 万，这一领域从业者需要具备哪些能力？","url":"https://www.zhihu.com/question/549057469"},{"title":"英国一 87 岁卖艺老人被当街围攻砍死，为何会出现这种惨剧？暴露出哪些问题？","url":"https://www.zhihu.com/question/549035123"},{"title":"目前大学讲师的待遇如何？","url":"https://www.zhihu.com/question/495127497"},{"title":"如何评价英伟达于2022年8月20日发布的《黑神话：悟空》实机演示视频?","url":"https://www.zhihu.com/question/549201009"},{"title":"有没有一瞬间，觉得自己这辈子完了？","url":"https://www.zhihu.com/question/270287048"},{"title":"养猫选公猫还是母猫?","url":"https://www.zhihu.com/question/548506442"},{"title":"面对气候变化问题，你有什么看法？","url":"https://www.zhihu.com/question/472727345"},{"title":"你一般选择什么方式疗愈自己的心情？","url":"https://www.zhihu.com/question/547105379"},{"title":"在2米深的泳池游泳和在20米深的泳池游泳有什么区别吗？","url":"https://www.zhihu.com/question/393242825"},{"title":"初三学习被指责假努力怎么办?","url":"https://www.zhihu.com/question/548926457"},{"title":"南京有哪些不错的咖啡馆？","url":"https://www.zhihu.com/question/20487943"},{"title":"《甄嬛传》中为什么安陵容被封为鹂妃反而很生气？","url":"https://www.zhihu.com/question/294012988"},{"title":"如何看待将顾客姓名登记为「畜生」，老百姓大药房回应称「会员信息录入有误」？","url":"https://www.zhihu.com/question/548919828"},{"title":"如何评价《一拳超人》重制版 215 话？","url":"https://www.zhihu.com/question/548934789"},{"title":"8 月 19 日海南新增本土确诊 469 例、无症状 732 例和疑似病例 1 例，目前疫情情况如何？","url":"https://www.zhihu.com/question/549185896"},{"title":"高铁上孩子吵闹，家长视而不见，你遇到过熊孩子和熟视无睹的家长吗？高铁如果出个带孩子车厢可行吗？","url":"https://www.zhihu.com/question/549079003"},{"title":"6 名「港独」组织成员承认「串谋颠覆国家政权罪」，将会受到什么法律惩罚，还有哪些信息值得关注？","url":"https://www.zhihu.com/question/549215381"},{"title":"长江流域为何「汛期反枯」？今年粮食产量会受影响吗？","url":"https://www.zhihu.com/question/549184360"},{"title":"专科大一应该为专升本准备什么？","url":"https://www.zhihu.com/question/489662764"},{"title":"为什么同学聚会越聚越尴尬？","url":"https://www.zhihu.com/question/20036820"}]